planingfsi/__init__.py
planingfsi/__main__.py
planingfsi/_version.py
planingfsi/cli.py
planingfsi/config.py
planingfsi/dictionary.py
planingfsi/figure.py
planingfsi/math_helpers.py
planingfsi/py.typed
planingfsi/simulation.py
planingfsi/solver.py
planingfsi/trig.py
planingfsi/unit.py
planingfsi/writers.py
planingfsi/fe/__init__.py
planingfsi/fe/felib.py
planingfsi/fe/femesh.py
planingfsi/fe/rigid_body.py
planingfsi/fe/structure.py
planingfsi/fe/substructure.py
planingfsi/potentialflow/__init__.py
planingfsi/potentialflow/pressureelement.py
planingfsi/potentialflow/pressurepatch.py
planingfsi/potentialflow/solver.py
planingfsi-0.5.1.dist-info/licenses/LICENSE
planingfsi-0.5.1.dist-info/METADATA
planingfsi-0.5.1.dist-info/WHEEL
planingfsi-0.5.1.dist-info/entry_points.txt
planingfsi-0.5.1.dist-info/top_level.txt
planingfsi-0.5.1.dist-info/RECORD
