Metadata-Version: 2.4
Name: planingfsi
Version: 0.5.1
Summary: Fluid-Structure Interaction for large deformation planing surfaces
Author-email: Matt Kramer <matthew.robert.kramer@gmail.com>
License: MIT
Project-URL: documentation, https://planingfsi.readthedocs.io
Project-URL: repository, https://github.com/mattkram/planingfsi
Classifier: License :: OSI Approved :: MIT License
Classifier: Programming Language :: Python
Classifier: Programming Language :: Python :: 3
Classifier: Programming Language :: Python :: 3.8
Classifier: Programming Language :: Python :: 3.9
Classifier: Programming Language :: Python :: 3.10
Classifier: Programming Language :: Python :: 3.11
Classifier: Topic :: Scientific/Engineering
Requires-Python: >=3.8
License-File: LICENSE
Requires-Dist: click<=8.3.1
Requires-Dist: click-log<=0.4.0
Requires-Dist: matplotlib<=3.10.8
Requires-Dist: numpy<=2.4.0
Requires-Dist: scipy<=1.16.3
Provides-Extra: dev
Requires-Dist: codecov; extra == "dev"
Requires-Dist: mypy; extra == "dev"
Requires-Dist: pytest; extra == "dev"
Requires-Dist: pytest-cov; extra == "dev"
Requires-Dist: tox; extra == "dev"
Dynamic: license-file
